fastapi_standalone_docs/__init__.py
fastapi_standalone_docs/scripts.py
fastapi_standalone_docs/standalone_docs.py
fastapi_standalone_docs/static/fastapi/LICENSE
fastapi_standalone_docs/static/fastapi/favicon.png
fastapi_standalone_docs/static/redoc/logo-mini.svg
fastapi_standalone_docs/static/redoc/redoc.standalone.js
fastapi_standalone_docs/static/redoc/redoc.standalone.js.LICENSE.txt
fastapi_standalone_docs/static/swagger/LICENSE
fastapi_standalone_docs/static/swagger/swagger-ui-bundle.js
fastapi_standalone_docs/static/swagger/swagger-ui.css
fastapi_standalone_docs/tests/__init__.py
fastapi_standalone_docs/tests/conftests.py
fastapi_standalone_docs/tests/test_standalone_docs.py
fastapi_standalone_docs-0.1.6.dist-info/LICENSE
fastapi_standalone_docs-0.1.6.dist-info/METADATA
fastapi_standalone_docs-0.1.6.dist-info/WHEEL
fastapi_standalone_docs-0.1.6.dist-info/entry_points.txt
fastapi_standalone_docs-0.1.6.dist-info/RECORD
