Metadata-Version: 2.1
Name: fastapi-standalone-docs
Version: 0.1.6
Summary: Host FastAPI Swagger UI and ReDoc without third party CDNs
Home-page: https://github.com/ioxiocom/fastapi-standalone-docs
License: MIT
Author: IOXIO Ltd
Requires-Python: >=3.8.1,<4.0
Classifier: License :: OSI Approved :: MIT License
Classifier: Programming Language :: Python :: 3
Classifier: Programming Language :: Python :: 3.9
Classifier: Programming Language :: Python :: 3.10
Classifier: Programming Language :: Python :: 3.11
Provides-Extra: scripts
Requires-Dist: fastapi (>=0.95.2,<1)
Project-URL: Repository, https://github.com/ioxiocom/fastapi-standalone-docs
